{
  "name": "k3s-helm-controller",
  "repo": "k3s-io/helm-controller",
  "version": "v0.17.3",
  "commit": "8c92459d41a6847ffaef0aab6be534f5cc7293c4",
  "builtAt": "2026-07-09T11:05:16.030Z",
  "fluxSchemaVersion": "0.10.0",
  "inputDigest": "sha256:03cd24b80138f41dcd299408e85eb2ff45ff66e8981c5ab4b5e9e1223c848a93",
  "filesDigest": "sha256:5d900c0317fd8be5ca26c3a0d2ac817bc0742e0f743170004bb84dcfa274671f",
  "kinds": {
    "helm.cattle.io/HelmChart": {
      "singular": "helmchart",
      "plural": "helmcharts",
      "shortNames": [
        "hc"
      ]
    },
    "helm.cattle.io/HelmChartConfig": {
      "singular": "helmchartconfig",
      "plural": "helmchartconfigs",
      "shortNames": [
        "hcc"
      ]
    }
  },
  "files": [
    "catalog/helm.cattle.io/helmchart_v1.fields.txt",
    "catalog/helm.cattle.io/helmchart_v1.json",
    "catalog/helm.cattle.io/helmchartconfig_v1.fields.txt",
    "catalog/helm.cattle.io/helmchartconfig_v1.json"
  ]
}
